LICENCE
MANIFEST.in
README.md
VERSION
setup.py
adminlte4/__init__.py
adminlte4/admin.py
adminlte4/apps.py
adminlte4/compat.py
adminlte4/models.py
adminlte4/tests.py
adminlte4/views.py
adminlte4/migrations/__init__.py
adminlte4/static/admin-lte/LICENSE
adminlte4/static/admin-lte/README.md
adminlte4/static/admin-lte/dist/css/adminlte.css
adminlte4/static/admin-lte/dist/css/adminlte.css.map
adminlte4/static/admin-lte/dist/css/adminlte.min.css
adminlte4/static/admin-lte/dist/css/adminlte.min.css.map
adminlte4/static/admin-lte/dist/css/alt/adminlte.components.css
adminlte4/static/admin-lte/dist/css/alt/adminlte.components.css.map
adminlte4/static/admin-lte/dist/css/alt/adminlte.components.min.css
adminlte4/static/admin-lte/dist/css/alt/adminlte.components.min.css.map
adminlte4/static/admin-lte/dist/css/alt/adminlte.core.css
adminlte4/static/admin-lte/dist/css/alt/adminlte.core.css.map
adminlte4/static/admin-lte/dist/css/alt/adminlte.core.min.css
adminlte4/static/admin-lte/dist/css/alt/adminlte.core.min.css.map
adminlte4/static/admin-lte/dist/css/alt/adminlte.extra-components.css
adminlte4/static/admin-lte/dist/css/alt/adminlte.extra-components.css.map
adminlte4/static/admin-lte/dist/css/alt/adminlte.extra-components.min.css
adminlte4/static/admin-lte/dist/css/alt/adminlte.extra-components.min.css.map
adminlte4/static/admin-lte/dist/css/alt/adminlte.pages.css
adminlte4/static/admin-lte/dist/css/alt/adminlte.pages.css.map
adminlte4/static/admin-lte/dist/css/alt/adminlte.pages.min.css
adminlte4/static/admin-lte/dist/css/alt/adminlte.pages.min.css.map
adminlte4/static/admin-lte/dist/css/alt/adminlte.plugins.css
adminlte4/static/admin-lte/dist/css/alt/adminlte.plugins.css.map
adminlte4/static/admin-lte/dist/css/alt/adminlte.plugins.min.css
adminlte4/static/admin-lte/dist/css/alt/adminlte.plugins.min.css.map
adminlte4/static/admin-lte/dist/img/AdminLTELogo.png
adminlte4/static/admin-lte/dist/img/avatar.png
adminlte4/static/admin-lte/dist/img/avatar2.png
django_adminlte4.egg-info/PKG-INFO
django_adminlte4.egg-info/SOURCES.txt
django_adminlte4.egg-info/dependency_links.txt
django_adminlte4.egg-info/requires.txt
django_adminlte4.egg-info/top_level.txt