Metadata-Version: 2.2
Name: django-adminlte4
Version: 0.1.1
Summary: Admin LTE templates, admin theme, and template tags for Django
Home-page: https://github.com/hehenischal/django-adminlte4
Author: hehenischal
Author-email: nischallc56@gmail.com
License: MIT
Requires-Python: >=3.6
License-File: LICENCE
Requires-Dist: django>=4.0
Dynamic: author
Dynamic: author-email
Dynamic: description
Dynamic: description-content-type
Dynamic: home-page
Dynamic: license
Dynamic: requires-dist
Dynamic: requires-python
Dynamic: summary
